cluster_tap/__init__.py
cluster_tap/cli.py
cluster_tap-1.0.10.dist-info/LICENSE
cluster_tap-1.0.10.dist-info/METADATA
cluster_tap-1.0.10.dist-info/WHEEL
cluster_tap-1.0.10.dist-info/entry_points.txt
cluster_tap-1.0.10.dist-info/top_level.txt
cluster_tap-1.0.10.dist-info/RECORD
