Metadata-Version: 2.1
Name: cluster-tap
Version: 1.0.10
Summary: A simple tool to manage your cluster
Author-email: sudo_free <ychong@petalmail.com>
Project-URL: Homepage, https://github.com/lasso-sustech/cluster-tap
Project-URL: Bug Reports, https://github.com/lasso-sustech/cluster-tap/issues
Keywords: cluster,lasso-sustech
Requires-Python: >=3.6
License-File: LICENSE
